miniglm.cp39-win_amd64.pyd
miniglm-0.3.3.dist-info/LICENSE
miniglm-0.3.3.dist-info/METADATA
miniglm-0.3.3.dist-info/WHEEL
miniglm-0.3.3.dist-info/top_level.txt
miniglm-0.3.3.dist-info/RECORD
