Metadata-Version: 2.1
Name: miniglm
Version: 0.3.3
Summary: UNKNOWN
Home-page: https://github.com/cprogrammer1994/miniglm
Author: Szabolcs Dombi
Author-email: cprogrammer1994@gmail.com
License: MIT
Platform: UNKNOWN
